Recursive_Symmetry_Aware_Materials_Microstructure_Explorer/__init__.py
Recursive_Symmetry_Aware_Materials_Microstructure_Explorer/select_model.py
Recursive_Symmetry_Aware_Materials_Microstructure_Explorer/util/__init__.py
Recursive_Symmetry_Aware_Materials_Microstructure_Explorer/util/google_images_download.py
Recursive_Symmetry_Aware_Materials_Microstructure_Explorer/util/image_collation.py
Recursive_Symmetry_Aware_Materials_Microstructure_Explorer/util/image_scraping.py
Recursive_Symmetry_Aware_Materials_Microstructure_Explorer/viz/__init__.py
Recursive_Symmetry_Aware_Materials_Microstructure_Explorer/viz/viz.py
Recursive_Symmetry_Aware_Materials_Microstructure_Explorer-0.0.17.dist-info/LICENSE
Recursive_Symmetry_Aware_Materials_Microstructure_Explorer-0.0.17.dist-info/METADATA
Recursive_Symmetry_Aware_Materials_Microstructure_Explorer-0.0.17.dist-info/WHEEL
Recursive_Symmetry_Aware_Materials_Microstructure_Explorer-0.0.17.dist-info/top_level.txt
Recursive_Symmetry_Aware_Materials_Microstructure_Explorer-0.0.17.dist-info/RECORD
